[
  {
    "id": 0,
    "category": "前菜",
    "menus": [
      {
        "id": 0,
        "url": "6shumori.jpg",
        "name": "お肉の前菜6種盛",
        "price": 1320,
        "description": ""
      },
      {
        "id": 1,
        "url": "namaham.jpg",
        "name": "切り立て生ハム",
        "price": 759,
        "description": ""
      },
      {
        "id": 2,
        "url": "dossari.jpg",
        "name": "どど～んとどっさり生ハムwith燻製チーズ",
        "price": 1320,
        "description": ""
      },
      {
        "id": 3,
        "url": "potesara.jpg",
        "name": "one'sのポテサラ",
        "price": 638,
        "description": ""
      },
      {
        "id": 31,
        "url": "pre.jpg",
        "name": "丸ごと食べれるガーリックシュリンプ",
        "price": 858,
        "description": ""
      },
      {
        "id": 30,
        "url": "magurotarutaru.png",
        "name": "マグロのたたきとアボカドのタルタル",
        "price": 990,
        "description": ""
      },
      {
        "id": 4,
        "url": "pre.jpg",
        "name": "厳選チーズの盛り合わせ",
        "price": 990,
        "description": ""
      },
      {
        "id": 5,
        "url": "pre.jpg",
        "name": "美桜鳥の自家製ハム",
        "price": 660,
        "description": ""
      },
      {
        "id": 6,
        "url": "gyutan.jpg",
        "name": "牛タンのカルパッチョ",
        "price": 770,
        "description": ""
      },
      {
        "id": 7,
        "url": "rebapate.jpg",
        "name": "白レバーのパテ",
        "price": 638,
        "description": ""
      },
      {
        "id": 8,
        "url": "pre.jpg",
        "name": "自家製ピクルス",
        "price": 418,
        "description": ""
      },
      {
        "id": 9,
        "url": "honeycream.jpg",
        "name": "無花果とクルミのハニークリームチーズ～バケット付～",
        "price": 748,
        "description": ""
      },
      {
        "id": 10,
        "url": "pre.jpg",
        "name": "オリーブ",
        "price": 385,
        "description": ""
      },
      {
        "id": 11,
        "url": "pre.jpg",
        "name": "燻製うずらの卵",
        "price": 385,
        "description": ""
      },
      {
        "id": 12,
        "url": "pre.jpg",
        "name": "ガーリックトースト",
        "price": 528,
        "description": ""
      },
      {
        "id": 13,
        "url": "nats.jpg",
        "name": "MIXナッツ",
        "price": 440,
        "description": ""
      },
      {
        "id": 14,
        "url": "pre.jpg",
        "name": "バケット",
        "price": 319,
        "description": ""
      }
    ]
  },
  {
    "id": 1,
    "category": "オススメ岩塩プレート",
    "menus": [
      {
        "id": 15,
        "url": "iberikos.jpg",
        "name": "イベリコ豚の岩塩プレート Sサイズ",
        "price": 748,
        "description": ""
      },
      {
        "id": 16,
        "url": "iberikod.jpg",
        "name": "イベリコ豚の岩塩プレート Dサイズ",
        "price": 1078,
        "description": ""
      },
      {
        "id": 17,
        "url": "pre.jpg",
        "name": "イベリコ豚の岩塩プレート Tサイズ",
        "price": 1408,
        "description": ""
      },
      {
        "id": 18,
        "url": "pre.jpg",
        "name": "イベリコ豚の岩塩プレート Mサイズ",
        "price": 1738,
        "description": ""
      }
    ]
  },
  {
    "id": 2,
    "category": "サラダ",
    "menus": [
      {
        "id": 19,
        "url": "pre.jpg",
        "name": "グリーンサラダ",
        "price": 770,
        "description": ""
      },
      {
        "id": 20,
        "url": "pre.jpg",
        "name": "牛タンのコンフィーとゴルゴンゾーラのサラダ",
        "price": 1100,
        "description": ""
      },
      {
        "id": 21,
        "url": "pre.jpg",
        "name": "こだわり野菜のバーニャカウダ",
        "price": 968,
        "description": ""
      }
    ]
  },
  {
    "id": 3,
    "category": "温菜",
    "menus": [
      {
        "id": 22,
        "url": "pre.jpg",
        "name": "フライドポテト",
        "price": 649,
        "description": ""
      },
      {
        "id": 23,
        "url": "pre.jpg",
        "name": "アンチョビガーリックポテト",
        "price": 759,
        "description": ""
      },
      {
        "id": 24,
        "url":"winesoup.jpg",
        "name": "ムール貝の白ワイン蒸し",
        "price": 990,
        "description": "残ったスープでリゾットもできます +495円"
      },
      {
        "id": 25,
        "url": "pre.jpg",
        "name": "キャベツのロースト",
        "price": 638,
        "description": ""
      } 
    ]
  },
{
    "id": 4,
    "category": "パスタ&飯",
    "menus": [
      {
        "id": 32,
        "url": "cheeserizo.jpg",
        "name": "パルミジャーノたっぷりチーズリゾット",
        "price": 990,
        "description": ""
      },
      {
        "id": 33,
        "url": "noririzo.jpg",
        "name": "生青海苔のリゾット",
        "price": 968,
        "description": ""
      },
      {
        "id": 34,
        "url": "unirizo.jpg",
        "name": "たっぷり雲丹のクリームリゾット",
        "price": 1210,
        "description": ""
      },
      {
        "id": 35,
        "url": "karubo.jpg",
        "name": "こだわり卵のカルボナーラ",
        "price": 1100,
        "description": "生パスタを使用しています"
      }
    ]
  },
  {
    "id": 5,
    "category": "デザート",
    "menus": [
      {
        "id": 27,
        "url": "pre.jpg",
        "name": "はちみつとクルミのヌガーグラッセ",
        "price": 715,
        "description": ""
      },
      {
        "id": 28,
        "url": "shocola.jpg",
        "name": "ガトーショコラ~バニラアイスのせ~",
        "price": 660,
        "description": ""
      },
      {
        "id": 29,
        "url": "pre.jpg",
        "name": "バニラアイス",
        "price": 330,
        "description": ""
      }
    ]
  }
]